spotkit/__init__.py
spotkit/__main__.py
spotkit/auth.py
spotkit/cli.py
spotkit/config.py
spotkit/exceptions.py
spotkit/exporter.py
spotkit/logger.py
spotkit/spotify_client.py
spotkit/storage.py
spotkit-1.0.1.dist-info/entry_points.txt
spotkit-1.0.1.dist-info/licenses/LICENSE
spotkit-1.0.1.dist-info/METADATA
spotkit-1.0.1.dist-info/WHEEL
spotkit-1.0.1.dist-info/RECORD
