Metadata-Version: 2.4
Name: spotkit
Version: 1.0.1
Summary: CLI toolbox for Spotify
License-Expression: MIT
License-File: LICENSE
Author: Guilherme Camacho
Author-email: guilherme.sousa.camacho@gmail.com
Requires-Python: >=3.11
Classifier: Development Status :: 4 - Beta
Classifier: Intended Audience :: End Users/Desktop
Classifier: License :: OSI Approved :: MIT License
Classifier: Programming Language :: Python :: 3
Classifier: Programming Language :: Python :: 3.11
Classifier: Programming Language :: Python :: 3.12
Classifier: Programming Language :: Python :: 3.13
Classifier: Programming Language :: Python :: 3.14
Classifier: Topic :: Multimedia :: Sound/Audio
Requires-Dist: python-dotenv (>=1.2.1,<2.0.0)
Requires-Dist: rich (>=14.2.0,<15.0.0)
Requires-Dist: spotipy (>=2.25.1,<3.0.0)
Requires-Dist: typer (>=0.20.0,<0.21.0)
Project-URL: Bug Tracker, https://github.com/GocasPT/SpotKit/issues
Project-URL: Homepage, https://github.com/GocasPT/SpotKit
Project-URL: Repository, https://github.com/GocasPT/SpotKit
